xia_meta_auth/__init__.py
xia_meta_auth/acl.cpython-310-darwin.so
xia_meta_auth/cache.cpython-310-darwin.so
xia_meta_auth/permission.cpython-310-darwin.so
xia_meta_auth/user.cpython-310-darwin.so
xia_meta_auth-0.1.3.dist-info/LICENSE.txt
xia_meta_auth-0.1.3.dist-info/METADATA
xia_meta_auth-0.1.3.dist-info/WHEEL
xia_meta_auth-0.1.3.dist-info/top_level.txt
xia_meta_auth-0.1.3.dist-info/RECORD
