Metadata-Version: 2.1
Name: xia-meta-auth
Version: 0.1.3
Summary: X-I-A Meta Authorization
Home-page: https://develop.x-i-a.com/docs/xia-meta-auth/0.1.3/index.html
Author: X-I-A
Author-email: admin@x-i-a.com
Requires-Python: >=3.9
License-File: LICENSE.txt
Requires-Dist: passlib
Requires-Dist: xia-engine-firestore
Requires-Dist: xia-meta
Requires-Dist: xia-cache
